{"adult":false,"also_known_as":[],"biography":"Matthew Posey was born on July 31, 1958 in Dallas, Texas, USA as Matthew Devon Posey. He is an actor and director, known for No Country for Old Men, Mr. Brooks, and The Magnificent Seven.","id":1219824,"imdb_id":"nm0692670","name":"Matthew Posey","place_of_birth":"Dallas, TX","popularity":0.6,"profile_path":"/bNTdROUqIqnCHD7PJFtX7l6oIfZ.jpg","credits":{"cast":[{"id":574963,"title":"This World Won't Break","character":"Lonnie Milligan","original_title":"This World Won't Break","poster_path":"/zNOWwdNd0SgwM3VOBbEfU111ile.jpg","release_date":"2019-04-12","adult":false},{"id":101315,"title":"A Killing in a Small Town","character":"Norman Billings","original_title":"A Killing in a Small Town","poster_path":"/5jTjFscM4nkTPSiu030kDgLwVI3.jpg","release_date":"1990-05-22","adult":false},{"id":267277,"title":"The Corpse Had a Familiar Face","character":"Sam","original_title":"The Corpse Had a Familiar Face","poster_path":"/nYRdVNzALpTMNe2jHWtLx1BayNh.jpg","release_date":"1994-03-27","adult":false},{"id":84071,"title":"Night Game","character":"Donnie","original_title":"Night Game","poster_path":"/yHRP6tCLMJNRC5KSzd42hKutksb.jpg","release_date":"1989-09-15","adult":false},{"id":34583,"title":"终极囚禁","character":"Parker","original_title":"The Final","poster_path":"/3jPSvaW9veHVeaEll9DH7eoJ634.jpg","release_date":"2010-01-28","adult":false},{"id":476406,"title":"Kansas","character":"Vernon","original_title":"Kansas","poster_path":"/wypzNDxEVU4sLBW5JYkdAdx83sh.jpg","release_date":"1995-07-27","adult":false},{"id":145486,"title":"In Broad Daylight","character":"Mayor Dan Austin","original_title":"In Broad Daylight","release_date":"1991-02-03","adult":false},{"id":3432,"title":"布鲁克斯先生","character":"","original_title":"Mr. Brooks","poster_path":"/yO9pNxyAFGb1i8cutXsYlTF5RT7.jpg","release_date":"2007-06-01","adult":false},{"id":333484,"title":"豪勇七蛟龙","character":"Hank Stoner","original_title":"The Magnificent Seven","poster_path":"/ezcS78TIjgr85pVdaPDd2rSPVNs.jpg","release_date":"2016-09-14","adult":false},{"id":11615,"title":"大卫·戈尔的一生","character":"Inmate Cook","original_title":"The Life of David Gale","poster_path":"/7tcAvE82JyxIi79cwQV5br90KVz.jpg","release_date":"2003-02-21","adult":false},{"id":6977,"title":"老无所依","character":"Sporting Goods Clerk","original_title":"No Country for Old Men","poster_path":"/6d5XOczc226jECq0LIX0siKtgHR.jpg","release_date":"2007-11-08","adult":false},{"id":74998,"title":"寻求正义","character":"Rabbit","original_title":"Seeking Justice","poster_path":"/oaNPAm5zz2q3jObxGywmvgWcvXr.jpg","release_date":"2011-09-02","adult":false}],"crew":[]},"images":{"profiles":[{"file_path":"/25i4A70sozFLQ1SQFdiKxTjZzK4.jpg","width":300,"height":450,"aspect_ratio":0.66666666666667,"vote_average":0,"vote_count":0},{"file_path":"/bNTdROUqIqnCHD7PJFtX7l6oIfZ.jpg","width":300,"height":450,"aspect_ratio":0.66666666666667,"vote_average":5.312,"vote_count":1}]},"external_ids":{"imdb_id":"nm0692670","freebase_mid":"/m/09vrhyq","freebase_id":"/en/matthew_posey","tvrage_id":207503}}