<?xml version="1.0" encoding="utf-8"?><Episode><id>6338865</id><Combined_episodenumber>1</Combined_episodenumber><Combined_season>8</Combined_season><DVD_chapter>0</DVD_chapter><DVD_discid></DVD_discid><DVD_episodenumber>1</DVD_episodenumber><DVD_season>8</DVD_season><Director>|Greg Nicotero|</Director><EpImgFlag></EpImgFlag><EpisodeName>仁慈</EpisodeName><EpisodeNumber>1</EpisodeNumber><FirstAired>2017-10-22</FirstAired><GuestStars></GuestStars><IMDB_ID>tt6156390</IMDB_ID><Language>zh</Language><Overview>亚历山大社区、山顶寨和神之国的联手，首次打败了来犯的尼根及其领导的救世军。简迪斯和其他投靠了尼根的拾荒者见形势不妙，也仓皇逃走。但这次胜利并没有伤及救世军的要害，瑞克也不会就此满足，一场更大的反击战即将展开。</Overview><ProductionCode></ProductionCode><Rating>7.9</Rating><RatingCount>810</RatingCount><SeasonNumber>8</SeasonNumber><Writer>|Scott M. Gimple|</Writer><absolute_number>100</absolute_number><airsafter_season>0</airsafter_season><airsbefore_episode>0</airsbefore_episode><airsbefore_season>0</airsbefore_season><filename>episodes/153021/6338865.jpg</filename><lastupdated>1563885367</lastupdated><seasonid>721203</seasonid><seriesid>153021</seriesid><thumb_added>2019-11-13 12:54:34</thumb_added><thumb_height>360</thumb_height><thumb_width>640</thumb_width></Episode>