{"adult":false,"also_known_as":[],"biography":"From Wikipedia, the free encyclopedia.\n\nMichael Edward \"Mike\" O'Malley (born October 31, 1966) is an American actor and playwright who has appeared in films and television series. He starred in the CBS comedy Yes, Dear. Prior to Yes Dear, he had a short-lived, self-named sitcom on NBC called The Mike O'Malley Show, in which he co-starred with his sister Kerry O'Malley, and also played the central character of short-lived WB sitcom Life with Roger. As of 2010, O'Malley has a recurring role on NBC's Parenthood, and a series regular role as Burt Hummel on FOX's Glee.\n\nDescription above from the Wikipedia article Mike O'Malley, licensed under CC-BY-SA, full list of contributors on Wikipedia.","birthday":"1966-10-31","id":87192,"imdb_id":"nm0005282","name":"Mike O'Malley","place_of_birth":"Boston - Massachusetts - USA","popularity":1.708,"profile_path":"/blpOdhEfAn9llt8gyYwIbqyaT2y.jpg","credits":{"cast":[{"id":367774,"title":"Above Freezing","character":"Artie","original_title":"Above Freezing","release_date":"1998-10-01","adult":false},{"id":34381,"title":"On Broadway","character":"Father Rolie O'Toole","original_title":"On Broadway","poster_path":"/3kn708IcIg2BWDOadrcSZ7HKNDP.jpg","release_date":"2007-04-25","adult":false},{"id":93837,"title":"女生部里的秘密","character":"Sam","original_title":"So Undercover","poster_path":"/abR6e0FaWwwcEJEM4PY5VvjwBr1.jpg","release_date":"2012-12-06","adult":false},{"id":15648,"title":"超完美男人","character":"Lenny Horton","original_title":"The Perfect Man","poster_path":"/8cE4xZkmE7NkWcgNk8A6dZ7Ou6Q.jpg","release_date":"2005-06-17","adult":false},{"id":57013,"title":"The Curse of the Bambino","character":"Himself","original_title":"The Curse of the Bambino","release_date":"2003-09-16","adult":false},{"id":288281,"title":"美满姻缘","character":"Bill Gaines","original_title":"A Good Marriage","poster_path":"/8odAiCOM9qwzzGRW69aKfAvK85q.jpg","release_date":"2014-10-03","adult":false},{"id":321741,"title":"震荡效应","character":"Daniel Sullivan","original_title":"Concussion","poster_path":"/azyXgo3R0UShwl8RAugAJ7fRHpc.jpg","release_date":"2015-11-12","adult":false},{"id":363676,"title":"萨利机长","character":"Charles Porter","original_title":"Sully","poster_path":"/mftyPBEYXAvkZYgjrgTTb7LSolT.jpg","release_date":"2016-09-07","adult":false},{"id":10468,"title":"28天","character":"Oliver","original_title":"28 Days","poster_path":"/8SOJsSg7cOLyqADsZxP3ZVKo03S.jpg","release_date":"2000-04-06","adult":false},{"id":49524,"title":"冥界警局","character":"Elliot","original_title":"R.I.P.D.","poster_path":"/fQ7CI5zmmhZlHuYBFKgK9w4hwlS.jpg","release_date":"2013-07-18","adult":false},{"id":52067,"title":"大假一场","character":"Mike Pyle","original_title":"Cedar Rapids","poster_path":"/86qSXEvbWbm6U5EtQwlMveoi5hL.jpg","release_date":"2011-02-11","adult":false},{"id":38167,"title":"美食、祈祷和恋爱","character":"Andy Shiraz","original_title":"Eat Pray Love","poster_path":"/9Hgiv1UEIjc8VwtOmFBCFzMs0er.jpg","release_date":"2010-08-12","adult":false},{"id":12596,"title":"空中塞车","character":"Pete","original_title":"Pushing Tin","poster_path":"/4bgeYDYqIb3M4pwuvbSQaJSTfYe.jpg","release_date":"1999-04-23","adult":false},{"id":119675,"title":"烛台背后","character":"Tracy Schnelker","original_title":"Behind the Candelabra","poster_path":"/iodt6hrewVXxR415PIjBeuZg3Qs.jpg","release_date":"2013-05-26","adult":false},{"id":11260,"title":"戴夫号飞船","character":"Knox","original_title":"Meet Dave","poster_path":"/3Qfav5aVRcZmq854olMjJ795JJ2.jpg","release_date":"2008-07-08","adult":false},{"id":629442,"title":"和爸爸在一起的3天","character":"Brick","original_title":"3 Days with Dad","poster_path":"/elwluzKR6BvB5WKBJqiLr5iv2hN.jpg","release_date":"2019-09-13","adult":false},{"id":8656,"title":"天地大冲撞","character":"Mike Perry","original_title":"Deep Impact","poster_path":"/a3vQS7JKqlOb3MdVJHuTCP9s7Mg.jpg","release_date":"1998-05-08","adult":false},{"id":4942,"title":"Leatherheads","character":"Mickey","original_title":"Leatherheads","poster_path":"/dl2yu8iuwG3dqbpjalm2odadRaH.jpg","release_date":"2008-03-24","adult":false}],"crew":[{"id":142314,"title":"Certainty","original_title":"Certainty","department":"Production","job":"Producer","poster_path":"/tfVorxfnTHKPgBZ1fXzosRPRdJg.jpg","release_date":"2011-09-16","adult":false},{"id":142314,"title":"Certainty","original_title":"Certainty","department":"Writing","job":"Screenplay","poster_path":"/tfVorxfnTHKPgBZ1fXzosRPRdJg.jpg","release_date":"2011-09-16","adult":false}]},"images":{"profiles":[{"file_path":"/blpOdhEfAn9llt8gyYwIbqyaT2y.jpg","width":643,"height":966,"aspect_ratio":0.6656314699793,"vote_average":5.246,"vote_count":2}]},"external_ids":{"imdb_id":"nm0005282","freebase_mid":"/m/032q8q","freebase_id":"/en/mike_omalley","tvrage_id":41743}}