{"adult":false,"also_known_as":[],"biography":"","id":2033714,"imdb_id":"nm0850190","name":"Giovanni Tarallo","popularity":0.6,"credits":{"cast":[{"id":33954,"title":"大鸟和小鸟","character":"Starving Peasant","original_title":"Uccellacci e uccellini","poster_path":"/jD6vUqAIfYmrCQ9GsCWPP5BgUD4.jpg","release_date":"1966-05-04","adult":false},{"id":938,"title":"黄昏双镖客","character":"Santa Cruz Telegraphist","original_title":"Per qualche dollaro in più","poster_path":"/wtKFORn2cXZm2lsT2xcyrPROrDe.jpg","release_date":"1965-12-18","adult":false},{"id":60543,"title":"C'era una volta","character":"","original_title":"C'era una volta","poster_path":"/AcpNXAYDXzUCl2sdhhUWqfePDUw.jpg","release_date":"1967-10-19","adult":false}],"crew":[]},"images":{"profiles":[]},"external_ids":{"imdb_id":"nm0850190","tvrage_id":0}}