{"adult":false,"also_known_as":[],"biography":"","id":30487,"imdb_id":"nm0188598","name":"Peter Crombie","popularity":0.6,"credits":{"cast":[{"id":292041,"title":"Smoothtalker","character":"Jack Perdue","original_title":"Smoothtalker","poster_path":"/c2LsccvjXtUEkolEGmAs8f8VuG2.jpg","release_date":"1990-12-01","adult":false},{"id":807,"title":"七宗罪","character":"Dr. O'Neill","original_title":"Se7en","poster_path":"/wOc1gj1L1tklTHRMTEsMEUjArZY.jpg","release_date":"1995-09-22","adult":false},{"id":335876,"title":"A Walton Easter","character":"Calvin Weeks","original_title":"A Walton Easter","poster_path":"/aI6mwJJ0T7MNOAblP2I8k9tK9wf.jpg","release_date":"1997-03-30","adult":false},{"id":7007,"title":"旭日追凶","character":"Greg","original_title":"Rising Sun","poster_path":"/jVWEeZ383peKxwE284AdyHqq6GH.jpg","release_date":"1993-07-30","adult":false},{"id":241,"title":"天生杀人狂","character":"Intense Cop","original_title":"Natural Born Killers","poster_path":"/a0UUOtgSWRmRIHRbkImxkgZYrF.jpg","release_date":"1994-08-25","adult":false},{"id":2604,"title":"生于7月4日","character":"Undercover Vet - Miami Convention","original_title":"Born on the Fourth of July","poster_path":"/hFoRzZa9GnOuwD5X7QvuO8hNsVk.jpg","release_date":"1989-03-02","adult":false}],"crew":[]},"images":{"profiles":[]},"external_ids":{"imdb_id":"nm0188598","freebase_mid":"/m/07q529","freebase_id":"/en/peter_crombie","tvrage_id":33103}}