{"adult":false,"also_known_as":[],"biography":"Drew Pearce (born 24 August 1975) is a British film writer, director and producer. He is best known for co-writing Iron Man 3, and writing the story to Mission: Impossible – Rogue Nation.\n\nDescription above from the Wikipedia Drew Pearce licensed under CC-BY-SA, full list of contributors on Wikipedia.","birthday":"1975-08-24","id":1239407,"imdb_id":"nm1510800","name":"Drew Pearce","place_of_birth":"Fife, Scotland, UK","popularity":0.784,"profile_path":"/yEOWkrpGXdtFWAYOY2dywSKHPKm.jpg","credits":{"cast":[{"id":259910,"title":"漫威影业：宇宙集结","character":"Himself","original_title":"Marvel Studios: Assembling a Universe","poster_path":"/uBFgpa03lpGK74plbT4TtdsgrV0.jpg","release_date":"2014-03-18","adult":false}],"crew":[{"id":253980,"title":"王者万岁","original_title":"Marvel One-Shot: All Hail the King","department":"Directing","job":"Director","poster_path":"/tDpud3Y3gWtmSdcVhN0t4WiwsIK.jpg","release_date":"2014-02-04","adult":false},{"id":406761,"title":"阿尔忒弥斯酒店","original_title":"Hotel Artemis","department":"Directing","job":"Director","poster_path":"/vaZMpZOhhkKOYz0MHCx4vDABwgP.jpg","release_date":"2018-06-07","adult":false},{"id":615679,"title":"Quartermaster","original_title":"Quartermaster","department":"Directing","job":"Director","release_date":"","adult":false},{"id":406761,"title":"阿尔忒弥斯酒店","original_title":"Hotel Artemis","department":"Production","job":"Executive Producer","poster_path":"/vaZMpZOhhkKOYz0MHCx4vDABwgP.jpg","release_date":"2018-06-07","adult":false},{"id":694301,"title":"Don't Mess with Julie Whitfield","original_title":"Don't Mess with Julie Whitfield","department":"Production","job":"Executive Producer","poster_path":"/rWMYlLZOioi9DCptXEtENQvDy6I.jpg","release_date":"2017-03-25","adult":false},{"id":68721,"title":"钢铁侠3","original_title":"Iron Man 3","department":"Writing","job":"Screenplay","poster_path":"/beHcxOJvRdFCCGRy2gE7pFPHte5.jpg","release_date":"2013-04-18","adult":false},{"id":253980,"title":"王者万岁","original_title":"Marvel One-Shot: All Hail the King","department":"Writing","job":"Screenplay","poster_path":"/tDpud3Y3gWtmSdcVhN0t4WiwsIK.jpg","release_date":"2014-02-04","adult":false},{"id":177677,"title":"碟中谍5：神秘国度","original_title":"Mission: Impossible - Rogue Nation","department":"Writing","job":"Story","poster_path":"/glzi3sDVg96A7pJD4eR6wSULn0x.jpg","release_date":"2015-07-23","adult":false},{"id":406761,"title":"阿尔忒弥斯酒店","original_title":"Hotel Artemis","department":"Writing","job":"Screenplay","poster_path":"/vaZMpZOhhkKOYz0MHCx4vDABwgP.jpg","release_date":"2018-06-07","adult":false},{"id":615679,"title":"Quartermaster","original_title":"Quartermaster","department":"Writing","job":"Writer","release_date":"","adult":false},{"id":384018,"title":"速度与激情：特别行动","original_title":"Fast & Furious Presents: Hobbs & Shaw","department":"Writing","job":"Screenplay","poster_path":"/j5Iv8Dh1VqizoXBEO3UNIYRoVVU.jpg","release_date":"2019-08-01","adult":false}]},"images":{"profiles":[{"file_path":"/yEOWkrpGXdtFWAYOY2dywSKHPKm.jpg","width":300,"height":450,"aspect_ratio":0.66666666666667,"vote_average":0,"vote_count":0}]},"external_ids":{"imdb_id":"nm1510800","freebase_mid":"/m/04y7pvf","freebase_id":"/en/drew_pearce","tvrage_id":0}}