{"adult":false,"backdrop_path":"/cJbD05kmKK6dBoqffnaKquuEodm.jpg","budget":0,"genres":[{"id":18,"name":"剧情"}],"homepage":"http://saitei-movie.jp/","id":488981,"imdb_id":"tt6563012","original_title":"最低。","overview":"根据在役 AV 女忧写作的小说改编版电影，聚焦三名 AV 女优的精神困境：从平凡的生活踏进 AV 新世界的主妇（森口彩乃 饰)，和母亲不和的人气 AV 女优彩乃（佐佐木心音 饰），无法接受现实的女高中生彩子（山田爱奈 饰）。","popularity":1.122,"poster_path":"/5CQtMMaMtYVDkPF6TlgkJfCSrcK.jpg","production_companies":[{"name":"Kadokawa Pictures","id":2073}],"production_countries":[{"iso_3166_1":"JP","name":"Japan"}],"release_date":"2017-11-25","revenue":0,"runtime":121,"spoken_languages":[{"iso_639_1":"ja","name":"日本語"}],"status":"Released","tagline":"","title":"最差劲","vote_average":6.2,"vote_count":5,"casts":{"cast":[{"id":2023195,"name":"Ayano Moriguchi","character":"Miho","order":0,"cast_id":11},{"id":1160546,"name":"Kokone Sasaki","character":"Ayano","order":1,"cast_id":3,"profile_path":"/fjrtydnHtUmZtB5f7XNnU5VH9d9.jpg"},{"id":2023196,"name":"Aina Yamada","character":"Ayako","order":2,"cast_id":12},{"id":96473,"name":"Shugo Oshinari","character":"","order":3,"cast_id":1},{"id":20708,"name":"Yôichirô Saitô","character":"","order":4,"cast_id":7,"profile_path":"/8HeLk41pIFHkaeKiZmfJy2pQCPP.jpg"},{"id":83528,"name":"Noriko Eguchi","character":"","order":5,"cast_id":6},{"id":20707,"name":"Makiko Watanabe","character":"Izumi","order":6,"cast_id":5},{"id":72606,"name":"Toshie Negishi","character":"Tomoe","order":7,"cast_id":2,"profile_path":"/fQCwQTzlxD7pTwn6Hav2WyXrwoE.jpg"},{"id":589222,"name":"Saki Takaoka","character":"Takako","order":8,"cast_id":4,"profile_path":"/hd86oZPkAU5nUf5scitBM7ZubuL.jpg"},{"id":509437,"name":"Ryu Morioka","character":"","order":9,"cast_id":14}],"crew":[{"id":106549,"name":"Takahisa Zeze","department":"Writing","job":"Screenplay","profile_path":"/mhUKffbVUEh706d3rkY4OnMnoxh.jpg"},{"id":106549,"name":"Takahisa Zeze","department":"Directing","job":"Director","profile_path":"/mhUKffbVUEh706d3rkY4OnMnoxh.jpg"},{"id":132937,"name":"Tomoyuki Maruo","department":"Art","job":"Art Direction"},{"id":1077993,"name":"Tomoko Ogawa","department":"Writing","job":"Writer"},{"id":1406714,"name":"Mana Sakura","department":"Writing","job":"Novel","profile_path":"/vbFuEilp2YUH4icAXQLyE7NQ5Gu.jpg"},{"id":1669908,"name":"Yasuyuki Sasaki","department":"Camera","job":"Director of Photography"},{"id":2221045,"name":"Yo Irie","department":"Sound","job":"Original Music Composer"}]},"releases":{"countries":[{"iso_3166_1":"HK","certification":"III","release_date":"2018-08-02T00:00:00.0000000Z"},{"iso_3166_1":"JP","certification":"R15+","release_date":"2017-11-25T00:00:00.0000000Z"}]},"images":{"backdrops":[{"file_path":"/cJbD05kmKK6dBoqffnaKquuEodm.jpg","width":2316,"height":1303,"aspect_ratio":1.77743668457406,"vote_average":0,"vote_count":0}],"posters":[{"file_path":"/pANOLn9xzOwfoIuw505qZlHuno2.jpg","width":2000,"height":3000,"iso_639_1":"en","aspect_ratio":0.6666666666666666,"vote_average":5.312,"vote_count":1},{"file_path":"/yoAto9LMjYFmdgrKvnSdgsRtHRv.jpg","width":2000,"height":3000,"iso_639_1":"en","aspect_ratio":0.6666666666666666,"vote_average":5.312,"vote_count":1},{"file_path":"/5CQtMMaMtYVDkPF6TlgkJfCSrcK.jpg","width":1000,"height":1444,"iso_639_1":"zh","aspect_ratio":0.6925207756232687,"vote_average":0,"vote_count":0}]},"keywords":{"keywords":[]},"trailers":{"quicktime":[],"youtube":[{"name":"【予告】最低。","size":"HD","source":"IuE3-D1AfDE"}]}}