{"adult":false,"also_known_as":["Фредрик Марч","Frederick March","Фредрік Марч"],"biography":"Fredric March (born Ernest Frederick McIntyre Bickel; August 31, 1897 – April 14, 1975) was an American actor, regarded as \"one of Hollywood's most celebrated, versatile stars of the 1930s and '40s.\" He won the Academy Award for Best Actor for Dr. Jekyll and Mr. Hyde (1931) and The Best Years of Our Lives (1946), as well as the Tony Award for Best Actor in a Play for Years Ago (1947) and Long Day's Journey into Night (1956). March is the only actor to have won both the Academy Award and the Tony Award twice.","birthday":"1897-08-31","deathday":"1975-04-15","id":13576,"imdb_id":"nm0545298","name":"Fredric March","place_of_birth":"Racine, Wisconsin, USA","popularity":1.689,"profile_path":"/3QzMI2O7NP2j45XBCoBl7o1KogN.jpg","credits":{"cast":[{"id":887,"title":"黄金时代","character":"Al Stephenson","original_title":"The Best Years of Our Lives","poster_path":"/ba6GlZzRlh7OHUitFnzUF1U7gpu.jpg","release_date":"1946-12-25","adult":false},{"id":3019,"title":"化身博士","character":"Dr. Henry Jekyll / Mr. Edward Hyde","original_title":"Dr. Jekyll and Mr. Hyde","poster_path":"/ucQxfeUc6MUHgCvDLDUNA1ZyOuQ.jpg","release_date":"1932-01-02","adult":false},{"id":25970,"title":"风流女妖","character":"Jonathan / Nathaniel / Samuel / Wallace Wooley","original_title":"I Married a Witch","poster_path":"/je47It0cpuFzM7wUReWlUQX0vXY.jpg","release_date":"1942-10-30","adult":false},{"id":37215,"title":"Death Takes a Holiday","character":"Prince Sirki / Death","original_title":"Death Takes a Holiday","poster_path":"/yXOndcgnf2BjiuOTKUcPWJirNVY.jpg","release_date":"1934-03-30","adult":false},{"id":37352,"title":"An Act of Murder","character":"Judge Calvin Cooke","original_title":"An Act of Murder","poster_path":"/gXBFUYIilIRkux3C64CqJRp4LB5.jpg","release_date":"1948-12-05","adult":false},{"id":37658,"title":"Anthony Adverse","character":"Anthony Adverse","original_title":"Anthony Adverse","poster_path":"/oQwKZwmkQ3g4nel05qoUehRvINe.jpg","release_date":"1936-08-29","adult":false},{"id":43893,"title":"Les Misérables","character":"Jean Valjean / Champmathieu","original_title":"Les Misérables","poster_path":"/9hSPMlFppQBCcDDECA0TgTL0F8k.jpg","release_date":"1935-04-20","adult":false},{"id":50067,"title":"Bedtime Story","character":"Luke Drake","original_title":"Bedtime Story","poster_path":"/48hgDJAQ6Tlvqjm66gjtHDs1Nap.jpg","release_date":"1941-12-25","adult":false},{"id":50070,"title":"The Sign of the Cross","character":"Marcus Superbus - Prefect of Rome","original_title":"The Sign of the Cross","poster_path":"/bkF5SY3QAP43lbqnUvpNT5BNHf6.jpg","release_date":"1932-11-30","adult":false},{"id":80771,"title":"There Goes My Heart","character":"Bill Spencer","original_title":"There Goes My Heart","poster_path":"/xLlp67tkE830mByd6QVMFiSC23P.jpg","release_date":"1938-10-14","adult":false},{"id":81110,"title":"The Eagle and the Hawk","character":"Jerry H. Young","original_title":"The Eagle and the Hawk","poster_path":"/ex2K1jWIuQrxooQdHAj9OxHOH3P.jpg","release_date":"1933-05-06","adult":false},{"id":84086,"title":"One Foot in Heaven","character":"William Spence","original_title":"One Foot in Heaven","poster_path":"/zsSHNsQaw2vbrvrJfxGY1FZ4Bfz.jpg","release_date":"1941-11-01","adult":false},{"id":77210,"title":"爱情无计","character":"Tom Chambers","original_title":"Design for Living","poster_path":"/h0T4FHsY51IccSGqGfaoYsd7hyx.jpg","release_date":"1933-12-29","adult":false},{"id":101297,"title":"Tomorrow, the World!","character":"Mike Frame","original_title":"Tomorrow, the World!","poster_path":"/ks9EB3iZzjGKREokNEvue8hP9VN.jpg","release_date":"1944-12-29","adult":false},{"id":104394,"title":"Death of a Salesman","character":"Willy Loman","original_title":"Death of a Salesman","poster_path":"/yJU8s7fOH2oYXqgsKPt3YzxTwIu.jpg","release_date":"1951-12-20","adult":false},{"id":99898,"title":"绳上人","character":"Karel Cernik","original_title":"Man on a Tightrope","poster_path":"/alW4hvzjGgdq74ZW4zoQNFA8OEh.jpg","release_date":"1953-04-01","adult":false},{"id":120522,"title":"Middle of the Night","character":"Jerry Kingsley","original_title":"Middle of the Night","poster_path":"/3iu42AR3wFifoqsglnk3RrdcX01.jpg","release_date":"1959-05-20","adult":false},{"id":120747,"title":"The Adventures of Mark Twain","character":"Samuel Langhorne Clemens (Mark Twain)","original_title":"The Adventures of Mark Twain","poster_path":"/6dLCA2cZtjbEukJzdUmapZC4b8U.jpg","release_date":"1944-05-03","adult":false},{"id":120977,"title":"The Dark Angel","character":"Alan Trent","original_title":"The Dark Angel","poster_path":"/wraq2Az4XIqwTm1NOVxa8BbjwkN.jpg","release_date":"1935-09-08","adult":false},{"id":140276,"title":"The Road to Glory","character":"Lieutenant Michel Denet","original_title":"The Road to Glory","release_date":"1936-09-04","adult":false},{"id":112951,"title":"The Affairs of Cellini","character":"Benvenuto Cellini","original_title":"The Affairs of Cellini","poster_path":"/gWBSiqSb9mCRodsKoD0DCBpsZFu.jpg","release_date":"1934-08-24","adult":false},{"id":114502,"title":"Albert Schweitzer","character":"Albert Schweitzer (english voice)","original_title":"Albert Schweitzer","poster_path":"/7JJxW6qGqHN6EZZIFVucEC2vsBz.jpg","release_date":"1957-12-22","adult":false},{"id":115425,"title":"The Buccaneer","character":"Jean Lafitte","original_title":"The Buccaneer","poster_path":"/5DO2nZNxvSYPt88nZiXOkiCz7R3.jpg","release_date":"1938-02-04","adult":false},{"id":157283,"title":"Christopher Columbus","character":"Christopher Columbus","original_title":"Christopher Columbus","poster_path":"/AhA9L5AgzjE7Y20cHWOoUeQzSXI.jpg","release_date":"1949-10-12","adult":false},{"id":159865,"title":"Strangers in Love","character":"Buddy Drake / Arthur Drake","original_title":"Strangers in Love","release_date":"1932-03-05","adult":false},{"id":161716,"title":"Another Part of the Forest","character":"Marcus Hubbard","original_title":"Another Part of the Forest","poster_path":"/e5Sw3nvaIP6jw0huhlCpQtKvi48.jpg","release_date":"1948-05-18","adult":false},{"id":194146,"title":"The Young Doctors","character":"Dr. Joseph Pearson","original_title":"The Young Doctors","poster_path":"/oggIxcuFLi66tCZfmEuCKxNu1gt.jpg","release_date":"1961-08-23","adult":false},{"id":206480,"title":"Trade Winds","character":"Sam Wye","original_title":"Trade Winds","poster_path":"/pCLpwMtj2Y2yHfsUiobY0TZJu5W.jpg","release_date":"1938-12-28","adult":false},{"id":218305,"title":"So Ends Our Night","character":"Josef Steiner","original_title":"So Ends Our Night","poster_path":"/mcfquwORtst95ii7v61eeq0atT2.jpg","release_date":"1941-02-27","adult":false},{"id":1908,"title":"风的传人","character":"Matthew Harrison Brady","original_title":"Inherit the Wind","poster_path":"/7oaHcF0gCOt2lKaT2zajhajP0Zo.jpg","release_date":"1960-06-24","adult":false},{"id":22692,"title":"一个明星的诞生","character":"Norman Maine","original_title":"A Star Is Born","poster_path":"/90EfCmXXWOs5dy7rHTNvGT9T8Kz.jpg","release_date":"1937-04-27","adult":false},{"id":27945,"title":"野狼","character":"Dr. Alex Favor","original_title":"Hombre","poster_path":"/wSMDgzHfFX65n5iLyxnegDXZHbc.jpg","release_date":"1967-03-21","adult":false},{"id":41461,"title":"The Iceman Cometh","character":"Harry Hope","original_title":"The Iceman Cometh","poster_path":"/7gYnHEzSepyA2tvknpwvhHvERLj.jpg","release_date":"1973-11-10","adult":false},{"id":42668,"title":"Alexander the Great","character":"Philip of Macedonia","original_title":"Alexander the Great","poster_path":"/yx2j2GcVi9Thk9vedLd4mq1kCn1.jpg","release_date":"1956-03-28","adult":false},{"id":43693,"title":"The Barretts of Wimpole Street","character":"Robert Browning","original_title":"The Barretts of Wimpole Street","poster_path":"/noVP6ZLDdAbZeWEbBEyW6C9VNCY.jpg","release_date":"1934-09-21","adult":false},{"id":37650,"title":"Nothing Sacred","character":"Wallace \"Wally\" Cook","original_title":"Nothing Sacred","poster_path":"/l0RiLSl7hupkt0NvBesMdIWr1LD.jpg","release_date":"1937-11-25","adult":false},{"id":43820,"title":"Susan and God","character":"Barrie Trexel","original_title":"Susan and God","poster_path":"/tAHCNhYbgoggJPuiMyBaJfFZLnk.jpg","release_date":"1940-06-07","adult":false},{"id":43875,"title":"Mary of Scotland","character":"Bothwell","original_title":"Mary of Scotland","poster_path":"/7FS5xsO80ZEEoZsn0v2X3TgiPf9.jpg","release_date":"1936-08-28","adult":false},{"id":18612,"title":"危急时刻","character":"Daniel C. Hilliard","original_title":"The Desperate Hours","poster_path":"/tM7U971CnpTCpTaX3s39pk32BHN.jpg","release_date":"1955-10-05","adult":false},{"id":80168,"title":"The Wild Party","character":"James 'Gil' Gilmore","original_title":"The Wild Party","poster_path":"/dpGlAJ2vmumNJjjrqXZd3frdnsj.jpg","release_date":"1929-04-06","adult":false},{"id":81107,"title":"Merrily We Go to Hell","character":"Jerry Corbett","original_title":"Merrily We Go to Hell","poster_path":"/qMunDEK0fMaeaourJgx2pIffmPn.jpg","release_date":"1932-06-10","adult":false},{"id":70881,"title":"Anna Karenina","character":"Count Vronsky","original_title":"Anna Karenina","poster_path":"/39bSsAvMGOgN8I5lt2rOQgAXsj7.jpg","release_date":"1935-08-30","adult":false},{"id":84303,"title":"Smilin' Through","character":"Kenneth Wayne","original_title":"Smilin' Through","poster_path":"/fUK1QEdq6eYZfaTRXjzyStTdEBT.jpg","release_date":"1932-09-24","adult":false},{"id":104209,"title":"The Royal Family of Broadway","character":"Tony Cavendish","original_title":"The Royal Family of Broadway","release_date":"1930-12-22","adult":false},{"id":104216,"title":"Sarah and Son","character":"Howard Vanning","original_title":"Sarah and Son","poster_path":"/3Yiu2CPWaF8w7bHGcHjPLQMcpwG.jpg","release_date":"1930-03-14","adult":false},{"id":136106,"title":"Honor Among Lovers","character":"Jerry Stafford","original_title":"Honor Among Lovers","poster_path":"/AqTJSD1HoZTU7rZki643dHJFRKc.jpg","release_date":"1931-02-28","adult":false},{"id":190260,"title":"The Marriage Playground","character":"Martin Boyne","original_title":"The Marriage Playground","release_date":"1929-12-12","adult":false},{"id":162957,"title":"Manslaughter","character":"Dan O'Bannon","original_title":"Manslaughter","release_date":"1930-07-22","adult":false},{"id":164264,"title":"True to the Navy","character":"Bull's Eye McCoy","original_title":"True to the Navy","release_date":"1930-05-25","adult":false},{"id":164828,"title":"Tonight Is Ours","character":"Sabien Pastal","original_title":"Tonight Is Ours","release_date":"1933-01-21","adult":false},{"id":166010,"title":"Laughter","character":"Paul Lockridge","original_title":"Laughter","poster_path":"/uTj0F1UfFdGdGEXH5PD9e4SG4yq.jpg","release_date":"1930-09-24","adult":false},{"id":187598,"title":"Good Dame","character":"Mace Townsley","original_title":"Good Dame","poster_path":"/qD451dc0SfxexKOiMrjY5F3QpgH.jpg","release_date":"1934-03-16","adult":false},{"id":179251,"title":"We Live Again","character":"Prince Dmitri Nekhlyudov","original_title":"We Live Again","release_date":"1934-11-01","adult":false},{"id":257110,"title":"All of Me","character":"Don Ellis","original_title":"All of Me","release_date":"1934-02-01","adult":false},{"id":183005,"title":"The 400 Million","character":"Narration (voice)","original_title":"The 400 Million","release_date":"1939-03-07","adult":false},{"id":359661,"title":"Victory","character":"Hendrik Heyst","original_title":"Victory","release_date":"1940-12-21","adult":false},{"id":361229,"title":"Island of Allah","character":"Himself / Narrator","original_title":"Island of Allah","release_date":"1956-06-26","adult":false},{"id":114498,"title":"The Titan: Story of Michelangelo","character":"Narrator","original_title":"The Titan: Story of Michelangelo","poster_path":"/qf6vIQFz9xPi3YkcnzDVJCJcJJD.jpg","release_date":"1950-01-01","adult":false},{"id":588121,"title":"Valley of the Tennessee","character":"Narrator (voice)","original_title":"Valley of the Tennessee","release_date":"1944-03-14","adult":false},{"id":596967,"title":"A Christmas Carol","character":"Narrator","original_title":"A Christmas Carol","poster_path":"/19gXRTxIYqXIW0A1PCYtwqb0WKm.jpg","release_date":"1959-12-27","adult":false},{"id":23518,"title":"Seven Days in May","character":"President Jordan Lyman","original_title":"Seven Days in May","poster_path":"/algRJ6CYYSzTLw75SCoQSEXqTYK.jpg","release_date":"1964-02-12","adult":false},{"id":28290,"title":"一袭灰衣万缕情","character":"Ralph Hopkins","original_title":"The Man in the Gray Flannel Suit","poster_path":"/zSsJcyfufRUx7eJ74NiW4Wiochc.jpg","release_date":"1956-04-12","adult":false},{"id":35580,"title":"The Bridges at Toko-Ri","character":"Rear Adm. George Tarrant","original_title":"The Bridges at Toko-Ri","poster_path":"/406FKtGHALh474r51Y0SRznd45B.jpg","release_date":"1954-12-01","adult":false},{"id":43336,"title":"Executive Suite","character":"Loren Phineas Shaw","original_title":"Executive Suite","poster_path":"/vEhIhrKu0R7nJq5rPIBoze896bY.jpg","release_date":"1954-04-30","adult":false},{"id":85255,"title":"...tick... tick... tick...","character":"Mayor Jeff Parks","original_title":"...tick... tick... tick...","poster_path":"/4G8siCz8McoztKEQNqERbhToeEO.jpg","release_date":"1970-01-09","adult":false},{"id":166888,"title":"I sequestrati di Altona","character":"Albrecht von Gerlach","original_title":"I sequestrati di Altona","release_date":"1962-10-30","adult":false},{"id":188419,"title":"Ladies Love Brutes","character":"Dwight Howell","original_title":"Ladies Love Brutes","release_date":"1930-05-14","adult":false},{"id":263389,"title":"Paris Bound","character":"Jim Hutton","original_title":"Paris Bound","release_date":"1929-08-03","adult":false},{"id":156441,"title":"My Sin","character":"Dick Grady","original_title":"My Sin","poster_path":"/3b6buXMWkkDbiDBwc636i7KrUjt.jpg","release_date":"1931-10-02","adult":false},{"id":309597,"title":"The Night Angel","character":"Rudek Berken","original_title":"The Night Angel","release_date":"1931-07-18","adult":false},{"id":119118,"title":"The Studio Murder Mystery","character":"Richard Hardell","original_title":"The Studio Murder Mystery","release_date":"1929-06-01","adult":false},{"id":315411,"title":"A Christmas Carol","character":"Ebenezer Scrooge","original_title":"A Christmas Carol","poster_path":"/d0Az3kaXnbeoW1JCtgXsCjtfWjr.jpg","release_date":"1954-01-01","adult":false},{"id":429535,"title":"Footlights and Fools","character":"Gregory Pyne","original_title":"Footlights and Fools","poster_path":"/5C5ysAtrT5N1Smi0U90aGhHUQDS.jpg","release_date":"1929-12-08","adult":false},{"id":336034,"title":"The Making of a Great Motion Picture","character":"","original_title":"The Making of a Great Motion Picture","poster_path":"/qXucaJg9U1wFUGSPRxECGRuOiWI.jpg","release_date":"1936-04-15","adult":false},{"id":672083,"title":"The Winslow Boy","character":"Arthur Winslow","original_title":"The Winslow Boy","release_date":"1958-11-13","adult":false},{"id":292749,"title":"The Devil","character":"Extra","original_title":"The Devil","release_date":"1921-01-17","adult":false},{"id":53832,"title":"It's a Big Country","character":"Joe Esposito","original_title":"It's a Big Country","release_date":"1951-11-20","adult":false},{"id":123473,"title":"Paramount on Parade","character":"Marine","original_title":"Paramount on Parade","release_date":"1930-04-22","adult":false},{"id":352420,"title":"Cavalcade of the Academy Awards","character":"(archive footage)","original_title":"Cavalcade of the Academy Awards","poster_path":"/s3O7Xn6NL5ZmM6LEKsfVO2fiiV7.jpg","release_date":"1940-07-31","adult":false},{"id":306796,"title":"Hollywood Remembers: Myrna Loy - So Nice to Come Home to","character":"(archive footage)","original_title":"Hollywood Remembers: Myrna Loy - So Nice to Come Home to","poster_path":"/coX8n1VD408FlJSSx0SKS3kxL6G.jpg","release_date":"1991-01-01","adult":false},{"id":202136,"title":"Complicated Women","character":"Himself (archive footage)","original_title":"Complicated Women","poster_path":"/fvQT0mlvu8cucYl3b7OPbrl85lJ.jpg","release_date":"2003-05-06","adult":false},{"id":168470,"title":"So You Want to Be in Pictures","character":"Himself--at Academy Awards (uncredited)","original_title":"So You Want to Be in Pictures","release_date":"1947-06-07","adult":false},{"id":159798,"title":"Make Me a Star","character":"Himself (uncredited)","original_title":"Make Me a Star","poster_path":"/xRMLDM9yR2hkc5rT1hB5BxsMaVj.jpg","release_date":"1932-07-01","adult":false},{"id":277129,"title":"The Spencer Tracy Legacy: A Tribute by Katharine Hepburn","character":"","original_title":"The Spencer Tracy Legacy: A Tribute by Katharine Hepburn","poster_path":"/orGASz2wKw95gUjLDItpEAg1v8G.jpg","release_date":"1986-03-09","adult":false},{"id":187998,"title":"Breakdowns of 1936","character":"Himself","original_title":"Breakdowns of 1936","poster_path":"/nEj7ukptZaaznhs8ijRPy5JT14m.jpg","release_date":"1936-12-30","adult":false},{"id":342221,"title":"Hollywood: Style Center of the World","character":"Himself","original_title":"Hollywood: Style Center of the World","poster_path":"/iPfa4Dn2N48l2oTd7aCHo4doZsJ.jpg","release_date":"1940-05-29","adult":false},{"id":94857,"title":"Brother, Can You Spare a Dime?","character":"(archive footage)","original_title":"Brother, Can You Spare a Dime?","poster_path":"/ztjdLw1BE4sUESKz2Jhn4mS6Qug.jpg","release_date":"1975-08-06","adult":false}],"crew":[]},"images":{"profiles":[{"file_path":"/wExEa29fej7x0euawBcimqEORsg.jpg","width":654,"height":981,"aspect_ratio":0.66666666666667,"vote_average":5.106,"vote_count":2},{"file_path":"/9EqVw5H1G6R8XgmRUkCFhH1jCYW.jpg","width":644,"height":966,"aspect_ratio":0.66666666666667,"vote_average":5.18,"vote_count":3},{"file_path":"/3QzMI2O7NP2j45XBCoBl7o1KogN.jpg","width":500,"height":750,"aspect_ratio":0.66666666666667,"vote_average":5.384,"vote_count":2}]},"external_ids":{"imdb_id":"nm0545298","freebase_mid":"/m/0h1_w","freebase_id":"/en/fredric_march","tvrage_id":114946}}