{"adult":false,"also_known_as":["Max Wrottesly"],"biography":"","id":1202683,"imdb_id":"nm0943031","name":"Max Wrottesley","popularity":0.603,"credits":{"cast":[{"id":86817,"title":"The Cosmonaut","character":"Andrei","original_title":"The Cosmonaut","poster_path":"/fNVFibdtV2yo3hrKKnD9JXs0zAM.jpg","release_date":"2013-05-17","adult":false},{"id":190652,"title":"The Division of Gravity","character":"","original_title":"The Division of Gravity","release_date":"2011-01-01","adult":false},{"id":342725,"title":"Love Me Do","character":"Phil","original_title":"Love Me Do","poster_path":"/3lOxOr55Cuf9CCeVVPqUR609f1y.jpg","release_date":"2015-10-15","adult":false},{"id":410399,"title":"The Final Quest","character":"Young Ronno","original_title":"The Final Quest","release_date":"2004-12-27","adult":false},{"id":410395,"title":"The Second Quest","character":"Young Ronno","original_title":"The Second Quest","release_date":"2004-04-05","adult":false},{"id":551517,"title":"Dirtymoney","character":"Gjon Duka","original_title":"Dirtymoney","poster_path":"/btZRoGR4JFTYqKf2GWoSAIL4z5h.jpg","release_date":"2013-09-28","adult":false},{"id":215830,"title":"开棺","character":"Michael","original_title":"Open Grave","poster_path":"/jgIdTI3KGpNPXsu10qXVuqQnMuH.jpg","release_date":"2013-08-13","adult":false},{"id":373342,"title":"The Quest","character":"young Ronno","original_title":"The Quest","release_date":"2002-04-01","adult":false},{"id":44826,"title":"雨果","character":"Train Engineer","original_title":"Hugo","poster_path":"/aluLMpPjOinLKqUuLkLL3mZqjy5.jpg","release_date":"2011-11-22","adult":false},{"id":118340,"title":"银河护卫队","character":"Sacrificed Nova Corpsman","original_title":"Guardians of the Galaxy","poster_path":"/sg1MnvxpdXn0ylkZCD6GMxNUkyO.jpg","release_date":"2014-07-30","adult":false},{"id":118289,"title":"戴安娜","character":"News of the World Photographer","original_title":"Diana","poster_path":"/a2fdd9ZcWeIh13PPNPnxKs2tbXm.jpg","release_date":"2013-09-19","adult":false}],"crew":[]},"images":{"profiles":[]},"external_ids":{"imdb_id":"nm0943031","freebase_mid":"/m/0kbyxcm","tvrage_id":66258}}