<?xml version="1.0" encoding="utf-8"?><Episode><id>6230000</id><Combined_episodenumber>5</Combined_episodenumber><Combined_season>6</Combined_season><DVD_chapter>0</DVD_chapter><DVD_discid></DVD_discid><DVD_episodenumber>5</DVD_episodenumber><DVD_season>6</DVD_season><Director>|Joel Novoa|</Director><EpImgFlag></EpImgFlag><EpisodeName>Deathstroke Returns</EpisodeName><EpisodeNumber>5</EpisodeNumber><FirstAired>2017-11-09</FirstAired><GuestStars>|Johann Urb|Kris Holden-Ried|Laara Sadiq|Liam Hall|Manu Bennett|Sydelle Noel|William Franklyn-Miller|</GuestStars><IMDB_ID>tt6493662</IMDB_ID><Language>zh</Language><Overview></Overview><ProductionCode>T27.13455</ProductionCode><Rating>7.3</Rating><RatingCount>203</RatingCount><SeasonNumber>6</SeasonNumber><Writer>|Ben Sokolowski|Spiro Skentzos|</Writer><absolute_number>120</absolute_number><airsafter_season>0</airsafter_season><airsbefore_episode>0</airsbefore_episode><airsbefore_season>0</airsbefore_season><filename>episodes/257655/6230000.jpg</filename><lastupdated>1585180493</lastupdated><seasonid>715406</seasonid><seriesid>257655</seriesid><thumb_added>2019-11-13 11:02:32</thumb_added><thumb_height>360</thumb_height><thumb_width>640</thumb_width></Episode>