<?xml version="1.0" encoding="utf-8"?><Episode><id>4712380</id><Combined_episodenumber>2</Combined_episodenumber><Combined_season>0</Combined_season><DVD_chapter>0</DVD_chapter><DVD_discid></DVD_discid><DVD_episodenumber>2</DVD_episodenumber><DVD_season>0</DVD_season><Director></Director><EpImgFlag></EpImgFlag><EpisodeName>Blood Rush: Mr. Queen Is Unavailable</EpisodeName><EpisodeNumber>2</EpisodeNumber><FirstAired>2013-11-06</FirstAired><GuestStars></GuestStars><IMDB_ID></IMDB_ID><Language>zh</Language><Overview></Overview><ProductionCode></ProductionCode><Rating>8</Rating><RatingCount>116</RatingCount><SeasonNumber>0</SeasonNumber><Writer></Writer><absolute_number>0</absolute_number><airsafter_season>0</airsafter_season><airsbefore_episode>6</airsbefore_episode><airsbefore_season>2</airsbefore_season><filename></filename><lastupdated>1585182438</lastupdated><seasonid>488842</seasonid><seriesid>257655</seriesid><thumb_added></thumb_added><thumb_height></thumb_height><thumb_width></thumb_width></Episode>