{"adult":false,"also_known_as":[],"biography":"","id":1090917,"imdb_id":"nm2968511","name":"Shozo Suzuki","popularity":0.6,"credits":{"cast":[{"id":130241,"title":"大曽根家の朝","character":"Yoshino","original_title":"大曽根家の朝","poster_path":"/7ef8woL4fEiwTn66boWf2OjoUCg.jpg","release_date":"1946-02-21","adult":false},{"id":18148,"title":"东京物语","character":"Jimuin","original_title":"東京物語","poster_path":"/rMPIrpEiWRVLLzSrXqrSsdeoPU4.jpg","release_date":"1953-11-03","adult":false},{"id":159412,"title":"壁あつき部屋","character":"","original_title":"壁あつき部屋","poster_path":"/qQNHosbsNUG58YtU0hlFjWGftAY.jpg","release_date":"1956-10-31","adult":false}],"crew":[]},"images":{"profiles":[]},"external_ids":{"imdb_id":"nm2968511","tvrage_id":0}}