{"adult":false,"also_known_as":[],"biography":"From Wikipedia, the free encyclopedia. Norbert Weisser (born July 9, 1946) is a German-born American film and theatre actor, probably most known for his many roles in Albert Pyun-directed movies (15 and counting). Weisser is a founding member of the Odyssey Theater and the Padua Hills Playwrights Festival, where he developed the role of Trickster in Murray Mednick's epic seven-hour The Coyote Cycle. He has played roles in theaters throughout Europe and the US, including Broadway, where he played Rode opposite Ed Harris in Ronald Harwood's Taking Sides at the Brooks Atkinson Theater. Most recently he played Oskar in John O'Keefe's Times Like These in San Francisco, Albany, New York and Los Angeles, where he received an Ovation Award, an LA Weekly Theater Award and an LA Drama Critics Circle nomination for his performance. Weisser has directed plays at the Magic Theater in San Francisco and at the Mark Taper Forum's New Playwrights Festival in Los Angeles. Recently he produced two Albert Pyun films, Infection and Cool Air. He is the father of fellow actor Morgan Weisser, who starred in both movies. Weisser's television credits include: Amelia Earhart: The Final Flight, Riders of the Purple Sage, My Antonia, From the Earth to the Moon, Alias, The Agency, NCIS, ER, and Ghost Whisperer. Description above from the Wikipedia article Norbert Weisser, licensed under CC-BY-SA, full list of contributors on Wikipedia.","birthday":"1946-07-09","homepage":"http://norbertweisser.com/index.htm","id":6701,"imdb_id":"nm0919256","name":"Norbert Weisser","place_of_birth":"Neu-Isenburg, Germany","popularity":0.678,"profile_path":"/m5vgCCT8vlp1yTS9BEbLQTFfrmx.jpg","credits":{"cast":[{"id":187222,"title":"Seeds of Tragedy","character":"Gunter","original_title":"Seeds of Tragedy","release_date":"1991-06-15","adult":false},{"id":249150,"title":"The Radicals","character":"Michael Sattler","original_title":"The Radicals","poster_path":"/5yH1kJy5z8urtbAFre6y6evTogy.jpg","release_date":"1990-01-01","adult":false},{"id":38849,"title":"Android","character":"Keller","original_title":"Android","poster_path":"/jsRWN56VUbwLwSFhE1ler2C4tei.jpg","release_date":"1982-10-15","adult":false},{"id":17135,"title":"Omega Doom","character":"The Head","original_title":"Omega Doom","poster_path":"/qv1pcO0reE85Doet0erBsOQEWPC.jpg","release_date":"1996-01-01","adult":false},{"id":55687,"title":"Adrenalin: Fear the Rush","character":"Cuzo","original_title":"Adrenalin: Fear the Rush","poster_path":"/azeZdo0MfO3ZcDa0GzgAC7zVP5m.jpg","release_date":"1996-11-29","adult":false},{"id":107096,"title":"挑战未来3：残酷猎杀","character":"Edson","original_title":"Nemesis 3: Time Lapse","poster_path":"/ghGwIJQpleJ16IfUZKmUJFUf46g.jpg","release_date":"1996-06-18","adult":false},{"id":146926,"title":"Heatseeker","character":"Tsui Tung","original_title":"Heatseeker","poster_path":"/k29krhQu93v4trIbRaayDdsFooj.jpg","release_date":"1995-06-27","adult":false},{"id":280495,"title":"Deceit","character":"Bailey / Farnsworth III","original_title":"Deceit","release_date":"1992-08-21","adult":false},{"id":36965,"title":"Infection","character":"Dr. Franks / Deputy Ben","original_title":"Infection","release_date":"2005-09-05","adult":false},{"id":140172,"title":"Cool Air","character":"Deltoid","original_title":"Cool Air","release_date":"2006-11-03","adult":false},{"id":88253,"title":"Down Twisted","character":"Alsandro Deltoid","original_title":"Down Twisted","poster_path":"/k8oGn18Sq4P1lpsghy77JoDEZJs.jpg","release_date":"1987-03-01","adult":false},{"id":129584,"title":"Sweet Lies","character":"Bill","original_title":"Sweet Lies","poster_path":"/sxjfAPahTJZeerROWmv00zy58tz.jpg","release_date":"1987-12-18","adult":false},{"id":243856,"title":"Blast","character":"Commando Rescuer","original_title":"Blast","poster_path":"/ljUWF51WFkJ5D005ETONOjdtgnv.jpg","release_date":"1997-03-13","adult":false},{"id":215339,"title":"The Secret of the Ice Cave","character":"Dr. Victor Talbot","original_title":"The Secret of the Ice Cave","release_date":"1989-01-01","adult":false},{"id":352413,"title":"Stark","character":"Powell","original_title":"Stark","release_date":"1985-04-10","adult":false},{"id":396602,"title":"In the Line of Duty: Siege at Marion","character":"John Singer","original_title":"In the Line of Duty: Siege at Marion","release_date":"1992-02-10","adult":false},{"id":47342,"title":"Radioactive Dreams","character":"Sternwood","original_title":"Radioactive Dreams","poster_path":"/fw53k6mlC604WSmhxCXpzYyqEPu.jpg","release_date":"1986-09-19","adult":false},{"id":149549,"title":"Bad Bizness","character":"Stephens","original_title":"Bad Bizness","poster_path":"/qxuMJFm740AT69SIcrraKf5xysj.jpg","release_date":"2003-11-11","adult":false},{"id":129251,"title":"The Incident","character":"Riefenstahl","original_title":"The Incident","poster_path":"/9K8wMPTFuTrA7VOY9qLJGcbTpT4.jpg","release_date":"1990-03-04","adult":false},{"id":249857,"title":"My Antonia","character":"Otto","original_title":"My Antonia","poster_path":"/rveTTyRKON1iJbUcVXKB2kGnmJd.jpg","release_date":"1995-01-01","adult":false},{"id":134048,"title":"Crazy Six","character":"Jerzy","original_title":"Crazy Six","poster_path":"/6qq4lKGwXZO34BEtzA6MbEsHDf6.jpg","release_date":"1997-11-01","adult":false},{"id":134806,"title":"Riders of the Purple Sage","character":"Deacon Tull","original_title":"Riders of the Purple Sage","poster_path":"/zch999pIcgRXc8MCcoLoolM4emJ.jpg","release_date":"1996-01-21","adult":false},{"id":426067,"title":"Midnight Cabaret","character":"Tony","original_title":"Midnight Cabaret","release_date":"1990-01-01","adult":false},{"id":281208,"title":"The Killers Within","character":"Bernhard Hiller","original_title":"The Killers Within","poster_path":"/rYN9L8sdRE17xrsZsO7ibUQxQ1U.jpg","release_date":"1995-01-01","adult":false},{"id":60173,"title":"挑战未来4：死亡天使","character":"Tokuda","original_title":"Nemesis 4: Death Angel","poster_path":"/uRsW3BigIIfDvabfH9Yl8OvcFEv.jpg","release_date":"1996-12-23","adult":false},{"id":28790,"title":"Arcade","character":"Albert","original_title":"Arcade","poster_path":"/rTOLYnFmqw4L4ye1DcWKS06ztfu.jpg","release_date":"1993-07-20","adult":false},{"id":8388,"title":"¡Three Amigos!","character":"German's Friend","original_title":"¡Three Amigos!","poster_path":"/gbstiT6QohTCifCGGyhk0CMqFhL.jpg","release_date":"1986-12-12","adult":false},{"id":424,"title":"辛德勒的名单","character":"Albert Hujar","original_title":"Schindler's List","poster_path":"/kukYu89yda6NrifW5kpLoOTU7YH.jpg","release_date":"1993-11-30","adult":false},{"id":1091,"title":"怪形","character":"Norwegian","original_title":"The Thing","poster_path":"/tzGY49kseSE9QAKk47uuDGwnSCu.jpg","release_date":"1982-06-25","adult":false},{"id":11327,"title":"午夜快车","character":"Erich","original_title":"Midnight Express","poster_path":"/vtXJf6DP2rk1yDx369MSAvwl9Cs.jpg","release_date":"1978-08-31","adult":false},{"id":13995,"title":"美国队长","character":"Alaskan surveyor","original_title":"Captain America","poster_path":"/f1FiCM7Hpqc8wz3ac9jD5jLfgAO.jpg","release_date":"1990-12-14","adult":false},{"id":15503,"title":"Around the Bend","character":"Walter","original_title":"Around the Bend","poster_path":"/dHjkHld4IxU8LVyv5ZvulO9wV9A.jpg","release_date":"2004-10-08","adult":false},{"id":10467,"title":"The Road to Wellville","character":"Dr. Spitzvogel","original_title":"The Road to Wellville","poster_path":"/zh7OVdFMpqpZ027z9RgVIwzxYjZ.jpg","release_date":"1994-10-28","adult":false},{"id":10439,"title":"女巫也疯狂","character":"Thackery's Father","original_title":"Hocus Pocus","poster_path":"/dklIskbHZKpMPZRSnWOdIKzDdXO.jpg","release_date":"1993-07-16","adult":false},{"id":521004,"title":"Beggarman, Thief","character":"Egon Hubisch","original_title":"Beggarman, Thief","poster_path":"/lN8SO2d2uh3D5Nc2QNkkBObKWz.jpg","release_date":"1979-11-26","adult":false},{"id":10249,"title":"火箭专家","character":"Zeppelin Pilot","original_title":"The Rocketeer","poster_path":"/2tDFRESFwKww1LHRE8W1Exj9edH.jpg","release_date":"1991-06-21","adult":false},{"id":13448,"title":"天使与魔鬼","character":"CERN Scientist","original_title":"Angels & Demons","poster_path":"/uxX48knT9dK8K82ZeLp9FO0EOUf.jpg","release_date":"2009-05-13","adult":false},{"id":12509,"title":"Pollock","character":"Hans Namuth","original_title":"Pollock","poster_path":"/azsBSw2zw2uNHiCjTnbe9TJVEDB.jpg","release_date":"2000-09-06","adult":false},{"id":15301,"title":"阴阳魔界","character":"Soldier No. 1 (segment \"Time Out\")","original_title":"Twilight Zone: The Movie","poster_path":"/mXqXyIVVfcLleoPYoJLK2H8Z9So.jpg","release_date":"1983-06-24","adult":false}],"crew":[]},"images":{"profiles":[{"file_path":"/m5vgCCT8vlp1yTS9BEbLQTFfrmx.jpg","width":666,"height":1000,"aspect_ratio":0.666,"vote_average":0,"vote_count":0}]},"external_ids":{"imdb_id":"nm0919256","freebase_mid":"/m/0281y5t","freebase_id":"/en/norbert_weisser","tvrage_id":8049}}