<?xml version="1.0" encoding="utf-8"?><Episode><id>7082952</id><Combined_episodenumber>1</Combined_episodenumber><Combined_season>1</Combined_season><DVD_chapter>0</DVD_chapter><DVD_discid></DVD_discid><DVD_episodenumber>0</DVD_episodenumber><DVD_season>0</DVD_season><Director>|Johan B. Renck|</Director><EpImgFlag></EpImgFlag><EpisodeName>1:23:45</EpisodeName><EpisodeNumber>1</EpisodeNumber><FirstAired>2019-05-06</FirstAired><GuestStars>|Philip Barantini|Ross Armstrong|</GuestStars><IMDB_ID>tt8162428</IMDB_ID><Language>zh</Language><Overview>1988年4月26日，瓦列里·列加索夫用录音带录下了他所知道的关于切尔诺贝利事故的一切真相，将录音带送出去后，他于1点23分45秒上吊自杀。正好两年前的1986年4月26日凌晨1点23分，乌克兰普里皮亚季的一名消防员瓦西里·伊格纳坚科的妻子柳德米拉目睹了切尔诺贝利核电站四号反应堆发生了爆炸。核电站的副总工程师迪亚特洛夫和轮班总管阿基莫夫试图了解爆炸原因，并报火警通知消防队来抑制屋顶上的火势。</Overview><ProductionCode></ProductionCode><Rating>8.6</Rating><RatingCount>135</RatingCount><SeasonNumber>1</SeasonNumber><Writer>|Craig Mazin|</Writer><absolute_number>1</absolute_number><airsafter_season>0</airsafter_season><airsbefore_episode>0</airsbefore_episode><airsbefore_season>0</airsbefore_season><filename>episodes/360893/7082952.jpg</filename><lastupdated>1578957475</lastupdated><seasonid>801960</seasonid><seriesid>360893</seriesid><thumb_added>2019-11-13 10:37:30</thumb_added><thumb_height>360</thumb_height><thumb_width>640</thumb_width></Episode>